torchsde_brownian/__init__.py
torchsde_brownian/brownian_base.py
torchsde_brownian/brownian_interval.py
torchsde_brownian/derived.py
torchsde_brownian/settings.py
torchsde_brownian/types.py
torchsde_brownian-0.2.5.dist-info/METADATA
torchsde_brownian-0.2.5.dist-info/WHEEL
torchsde_brownian-0.2.5.dist-info/licenses/LICENSE
torchsde_brownian-0.2.5.dist-info/RECORD
