Metadata-Version: 2.1
Name: torchsde-brownian
Version: 0.2.5
Summary: Brownian motion implementations extracted from torchsde
Project-URL: Homepage, https://github.com/akx/torchsde-brownian
Author-email: Xuechen Li <lxuechen@cs.stanford.edu>, Patrick Kidger <hello@kidger.site>, Aarni Koskela <akx@iki.fi>
License-Expression: Apache-2.0
License-File: LICENSE
Classifier: License :: OSI Approved :: Apache Software License
Classifier: Programming Language :: Python :: 3
Requires-Python: >=3.6
Requires-Dist: numpy>=1.19
Requires-Dist: torch>=1.6.0
Requires-Dist: trampoline>=0.1.2
Provides-Extra: test
Requires-Dist: pytest; extra == 'test'
Requires-Dist: scipy>=1.5; extra == 'test'
